vss_ctx_rag/base/__init__.py
vss_ctx_rag/base/function.py
vss_ctx_rag/base/tool.py
vss_ctx_rag/context_manager/__init__.py
vss_ctx_rag/context_manager/context_manager.py
vss_ctx_rag/context_manager/context_manager_handler.py
vss_ctx_rag/functions/__init__.py
vss_ctx_rag/functions/function_factory.py
vss_ctx_rag/functions/notification/__init__.py
vss_ctx_rag/functions/notification/notifier.py
vss_ctx_rag/functions/rag/__init__.py
vss_ctx_rag/functions/rag/config.py
vss_ctx_rag/functions/rag/prompt.py
vss_ctx_rag/functions/rag/foundation_rag/__init__.py
vss_ctx_rag/functions/rag/foundation_rag/foundation_ingestion_func.py
vss_ctx_rag/functions/rag/foundation_rag/foundation_retrieval_func.py
vss_ctx_rag/functions/rag/graph_rag/__init__.py
vss_ctx_rag/functions/rag/graph_rag/constants.py
vss_ctx_rag/functions/rag/graph_rag/planner_constants.py
vss_ctx_rag/functions/rag/graph_rag/prompt.py
vss_ctx_rag/functions/rag/graph_rag/ingestion/__init__.py
vss_ctx_rag/functions/rag/graph_rag/ingestion/base.py
vss_ctx_rag/functions/rag/graph_rag/ingestion/graph_ingestion.py
vss_ctx_rag/functions/rag/graph_rag/retrieval/__init__.py
vss_ctx_rag/functions/rag/graph_rag/retrieval/adv_base.py
vss_ctx_rag/functions/rag/graph_rag/retrieval/adv_graph_retrieval.py
vss_ctx_rag/functions/rag/graph_rag/retrieval/base.py
vss_ctx_rag/functions/rag/graph_rag/retrieval/gnn_retrieval.py
vss_ctx_rag/functions/rag/graph_rag/retrieval/graph_retrieval.py
vss_ctx_rag/functions/rag/graph_rag/retrieval/graph_retrieval_base.py
vss_ctx_rag/functions/rag/graph_rag/retrieval/planner.py
vss_ctx_rag/functions/rag/graph_rag/retrieval/planner_retrieval.py
vss_ctx_rag/functions/rag/graph_rag/tools/__init__.py
vss_ctx_rag/functions/rag/graph_rag/tools/graph_search_tool.py
vss_ctx_rag/functions/rag/vector_rag/__init__.py
vss_ctx_rag/functions/rag/vector_rag/vector_ingestion_func.py
vss_ctx_rag/functions/rag/vector_rag/vector_retrieval_func.py
vss_ctx_rag/functions/rag/vlm_retrieval/__init__.py
vss_ctx_rag-1.0.1.dist-info/licenses/LICENSE
vss_ctx_rag-1.0.1.dist-info/licenses/LICENSE.3rdparty
vss_ctx_rag-1.0.1.dist-info/METADATA
vss_ctx_rag-1.0.1.dist-info/WHEEL
vss_ctx_rag-1.0.1.dist-info/top_level.txt
vss_ctx_rag-1.0.1.dist-info/RECORD
