Metadata-Version: 2.4
Name: vss_ctx_rag
Version: 1.0.1
Project-URL: Homepage, https://github.com/NVIDIA/context-aware-rag
Project-URL: Documentation, https://nvidia.github.io/context-aware-rag/index.html
Project-URL: Repository, https://github.com/NVIDIA/context-aware-rag
Requires-Python: >=3.12
License-File: LICENSE
License-File: LICENSE.3rdparty
Requires-Dist: openai<2.0.0,>=1.68.2
Requires-Dist: langchain_core>=0.3.72
Requires-Dist: langchain>=0.3.27
Requires-Dist: langchain_community>=0.3.27
Requires-Dist: langchain_milvus>=0.2.1
Requires-Dist: langchain-openai>=0.3.10
Requires-Dist: langchain-experimental>=0.3.4
Requires-Dist: langchain-nvidia-ai-endpoints>=0.3.13
Requires-Dist: pymilvus>=2.5.14
Requires-Dist: pymilvus-model==0.3.2
Requires-Dist: python-multipart==0.0.18
Requires-Dist: pydantic>=2.11.7
Requires-Dist: pyyaml>=6.0.2
Requires-Dist: protobuf>=5.29.5
Requires-Dist: redis==5.2.1
Requires-Dist: unstructured[all-docs]>=0.15.1
Requires-Dist: uvicorn[standard]==0.32.0
Requires-Dist: fastapi<0.116.0,>=0.115.4
Requires-Dist: requests<2.33.0,>=2.32.3
Requires-Dist: jsonschema<4.23.0,>=4.22.0
Requires-Dist: schema<0.8.0,>=0.7.7
Requires-Dist: json-repair==0.30.2
Requires-Dist: opentelemetry-sdk>=1.28.2
Requires-Dist: opentelemetry-api>=1.28.2
Requires-Dist: opentelemetry-exporter-otlp-proto-http>=1.28.2
Requires-Dist: opentelemetry-instrumentation-fastapi>=0.49b2
Requires-Dist: nvtx==0.2.11
Requires-Dist: matplotlib==3.9.4
Requires-Dist: torch<3.0.0,>=2.0.0
Requires-Dist: safetensors==0.4.4
Requires-Dist: minio==7.2.15
Requires-Dist: pyaml-env<2.0.0,>=1.2.1
Requires-Dist: bleach==6.2.0
Requires-Dist: dataclass-wizard==0.27.0
Requires-Dist: pdfplumber>=0.6
Requires-Dist: nvidia-rag>=2.2.2
Requires-Dist: openinference-semantic-conventions>=0.1.21
Requires-Dist: openinference-instrumentation-openai>=0.1.30
Requires-Dist: openinference-instrumentation-langchain>=0.1.44
Requires-Dist: neo4j>=5.24
Requires-Dist: fastmcp>=2.11.3
Requires-Dist: langgraph>=0.6.4
Requires-Dist: langchain-elasticsearch>=0.3.2
Provides-Extra: docs
Requires-Dist: ipython~=8.31; extra == "docs"
Requires-Dist: myst-parser~=4.0; extra == "docs"
Requires-Dist: nbsphinx~=0.9; extra == "docs"
Requires-Dist: nvidia-sphinx-theme>=0.0.7; extra == "docs"
Requires-Dist: sphinx~=8.2; extra == "docs"
Requires-Dist: sphinx-copybutton>=0.5; extra == "docs"
Requires-Dist: sphinx-autoapi>=3.6; extra == "docs"
Requires-Dist: vale==3.9.5; extra == "docs"
Requires-Dist: setuptools-scm>=8.1.0; extra == "docs"
Requires-Dist: sphinxcontrib-mermaid>=1.0.0; extra == "docs"
Provides-Extra: arango
Requires-Dist: vss_ctx_rag_arango; extra == "arango"
Provides-Extra: nat
Requires-Dist: vss_ctx_rag_nat; extra == "nat"
Dynamic: license-file
